scaraplate/__init__.py
scaraplate/__main__.py
scaraplate/compat.py
scaraplate/config.py
scaraplate/cookiecutter.py
scaraplate/fields.py
scaraplate/gitremotes.py
scaraplate/py.typed
scaraplate/rollup.py
scaraplate/strategies.py
scaraplate/template.py
scaraplate/automation/__init__.py
scaraplate/automation/base.py
scaraplate/automation/git.py
scaraplate/automation/gitlab.py
scaraplate-0.5.dist-info/LICENSE
scaraplate-0.5.dist-info/METADATA
scaraplate-0.5.dist-info/WHEEL
scaraplate-0.5.dist-info/entry_points.txt
scaraplate-0.5.dist-info/top_level.txt
scaraplate-0.5.dist-info/RECORD
