Metadata-Version: 2.1
Name: scaraplate
Version: 0.5
Summary: Scaraplate is a wrapper around cookiecutter which allows to repeatedly rollup project templates onto concrete projects.
Home-page: https://github.com/rambler-digital-solutions/scaraplate
Author: Usermodel @ Rambler&Co
Author-email: um@rambler-co.ru
Maintainer: Kostya Esmukov
Maintainer-email: kostya@esmukov.net
License: MIT
Project-URL: Docs, https://scaraplate.readthedocs.io/
Project-URL: Issue Tracker, https://github.com/rambler-digital-solutions/scaraplate/issues
Project-URL: Source Code, https://github.com/rambler-digital-solutions/scaraplate
Classifier: Development Status :: 4 - Beta
Classifier: Environment :: Console
Classifier: Intended Audience :: Developers
Classifier: License :: OSI Approved :: MIT License
Classifier: Natural Language :: English
Classifier: Operating System :: OS Independent
Classifier: Programming Language :: Python :: 3 :: Only
Classifier: Topic :: Software Development
Requires-Python: >=3.7
License-File: LICENSE
Requires-Dist: click (>=6)
Requires-Dist: cookiecutter (<3,>=1.6)
Requires-Dist: jinja2 (<4,>=2.7)
Requires-Dist: marshmallow (<4,>=2.15)
Requires-Dist: packaging
Requires-Dist: pyyaml (>=3)
Requires-Dist: setuptools
Provides-Extra: develop
Requires-Dist: black (==23.3.0) ; extra == 'develop'
Requires-Dist: coverage (==7.2.7) ; extra == 'develop'
Requires-Dist: flake8 (==5.0.4) ; extra == 'develop'
Requires-Dist: isort (==5.11.5) ; extra == 'develop'
Requires-Dist: mypy (==1.4.1) ; extra == 'develop'
Requires-Dist: pylint (==2.17.4) ; extra == 'develop'
Requires-Dist: pytest (==7.4.0) ; extra == 'develop'
Requires-Dist: sphinx-rtd-theme (==1.2.2) ; extra == 'develop'
Requires-Dist: sphinx (==4.3.2) ; extra == 'develop'
Requires-Dist: types-PyYAML ; extra == 'develop'
Requires-Dist: types-setuptools ; extra == 'develop'
Provides-Extra: gitlab
Requires-Dist: python-gitlab (<4,>=1.6.0) ; extra == 'gitlab'
